check_zfs_snapshot/__init__.py
check_zfs_snapshot-2.1.0.dist-info/WHEEL
check_zfs_snapshot-2.1.0.dist-info/entry_points.txt
check_zfs_snapshot-2.1.0.dist-info/METADATA
check_zfs_snapshot-2.1.0.dist-info/RECORD
