Metadata-Version: 2.3
Name: check_zfs_snapshot
Version: 2.1.0
Summary: A monitoring plugin that checks how long ago the last snapshot of ZFS datasets was created.
Author: Josef Friedrich
Author-email: Josef Friedrich <josef@friedrich.rocks>
License: MIT
Classifier: Development Status :: 5 - Production/Stable
Classifier: Topic :: Utilities
Classifier: License :: OSI Approved :: MIT License
Classifier: Programming Language :: Python :: 3 :: Only
Classifier: Programming Language :: Python :: 3
Classifier: Programming Language :: Python :: 3.10
Classifier: Programming Language :: Python :: 3.11
Classifier: Programming Language :: Python :: 3.12
Classifier: Programming Language :: Python :: 3.13
Classifier: Programming Language :: Python :: 3.14
Requires-Dist: nagiosplugin>=1,<2
Requires-Python: >=3.10, <4
Project-URL: Repository, https://github.com/Josef-Friedrich/check_zfs_snapshot
